prism/__init__.py
prism/api/__init__.py
prism/api/models.py
prism/api/routers/__init__.py
prism/api/routers/crud.py
prism/api/routers/functions.py
prism/api/routers/health.py
prism/api/routers/metadata.py
prism/api/routers/views.py
prism/cache.py
prism/config.py
prism/core/__init__.py
prism/core/introspection/__init__.py
prism/core/introspection/base.py
prism/core/introspection/postgres.py
prism/core/models/__init__.py
prism/core/models/enums.py
prism/core/models/functions.py
prism/core/models/tables.py
prism/core/query/__init__.py
prism/core/query/builder.py
prism/core/query/operators.py
prism/core/types/__init__.py
prism/core/types/mapping.py
prism/core/types/utils.py
prism/db/__init__.py
prism/db/client.py
prism/prism.py
prism/py.typed
prism/ui.py
prism_py-0.0.13.dist-info/WHEEL
prism_py-0.0.13.dist-info/entry_points.txt
prism_py-0.0.13.dist-info/METADATA
prism_py-0.0.13.dist-info/RECORD
