Metadata-Version: 2.3
Name: prism-py
Version: 0.0.13
Summary: Automatic API generator that creates a REST API mirror of a database
Keywords: api,rest,database,orm,codegen
Author: Yrrrrrf
Author-email: Yrrrrrf <fer.rezac@outlook.com>
License: MIT
Classifier: Development Status :: 3 - Alpha
Classifier: Intended Audience :: Developers
Classifier: Programming Language :: Python :: 3.10
Classifier: Programming Language :: Python :: 3.11
Classifier: Programming Language :: Python :: 3.12
Classifier: Programming Language :: Python :: 3.13
Classifier: Programming Language :: Python :: 3.14
Classifier: Topic :: Database
Classifier: Topic :: Internet :: WWW/HTTP :: WSGI :: Application
Classifier: Topic :: Software Development :: Code Generators
Classifier: Typing :: Typed
Requires-Dist: fastapi>=0.121.0
Requires-Dist: sqlalchemy>=2.0.44
Requires-Dist: psycopg2-binary>=2.9.11
Requires-Dist: pydantic>=2.12.4
Requires-Dist: rich>=14.2.0
Requires-Python: >=3.10
Project-URL: Download, https://github.com/Yrrrrrf/prism-py/releases
Project-URL: Repository, https://github.com/Yrrrrrf/prism-py
